{
  "region": "Scotland",
  "category": "leafy",
  "crops": [
    {
      "name": "Lettuce – looseleaf",
      "category": "leafy",
      "months": {
        "sow": [
          1,
          2,
          3,
          4,
          5,
          6,
          7,
          8
        ],
        "plant": [
          3,
          4,
          5,
          6,
          7
        ],
        "harvest": [
          4,
          5,
          6,
          7,
          8,
          9
        ]
      },
      "details": {
        "planting": {
          "seed_depth_cm": 0.5,
          "spacing_cm": {
            "in_row": 15,
            "between_rows": 25
          }
        },
        "sunlight": "Sun spring/autumn; part shade summer",
        "where": "Pots, window boxes, beds",
        "protection": {
          "fleece": "protect from cold snaps; harden off before planting out"
        },
        "tips": [
          "Succession sow every 2–3 weeks",
          "Keep evenly moist"
        ]
      },
      "containers": {
        "min_pot_diameter_cm": 22,
        "min_depth_cm": 18
      },
      "notes": ""
    },
    {
      "name": "Lettuce – butterhead",
      "category": "leafy",
      "months": {
        "sow": [
          1,
          2,
          3,
          4,
          5,
          7
        ],
        "plant": [
          3,
          4,
          5,
          7
        ],
        "harvest": [
          4,
          5,
          6,
          7,
          8
        ]
      },
      "details": {
        "planting": {
          "seed_depth_cm": 0.5,
          "spacing_cm": {
            "in_row": 20,
            "between_rows": 25
          }
        },
        "sunlight": "Sun/part",
        "where": "Pots/beds",
        "protection": {
          "fleece": "protect from cold snaps; harden off before planting out"
        },
        "tips": [
          "Firm in well to reduce bolting"
        ]
      },
      "containers": {
        "min_pot_diameter_cm": 24,
        "min_depth_cm": 20
      },
      "notes": ""
    },
    {
      "name": "Lettuce – romaine/cos",
      "category": "leafy",
      "months": {
        "sow": [
          1,
          2,
          3,
          4,
          5
        ],
        "plant": [
          3,
          4,
          5
        ],
        "harvest": [
          5,
          6,
          7
        ]
      },
      "details": {
        "planting": {
          "seed_depth_cm": 0.8,
          "spacing_cm": {
            "in_row": 25,
            "between_rows": 30
          }
        },
        "sunlight": "Sun (cool), part shade in heat",
        "where": "Beds/boxes",
        "protection": {
          "fleece": "protect from cold snaps; harden off before planting out"
        },
        "tips": [
          "Water at roots; avoid heat stress"
        ]
      },
      "containers": {
        "min_pot_diameter_cm": 24,
        "min_depth_cm": 22
      },
      "notes": ""
    },
    {
      "name": "Lettuce – iceberg/crisphead",
      "category": "leafy",
      "months": {
        "sow": [
          1,
          2,
          3,
          4
        ],
        "plant": [
          3,
          4
        ],
        "harvest": [
          5,
          6,
          7
        ]
      },
      "details": {
        "planting": {
          "seed_depth_cm": 0.8,
          "spacing_cm": {
            "in_row": 25,
            "between_rows": 30
          }
        },
        "sunlight": "Sun (cool)",
        "where": "Beds/boxes",
        "protection": {
          "fleece": "protect from cold snaps; harden off before planting out"
        },
        "tips": [
          "Needs steady cool to heart well"
        ]
      },
      "containers": {
        "min_pot_diameter_cm": 26,
        "min_depth_cm": 22
      },
      "notes": ""
    },
    {
      "name": "Cut-and-come salad mix",
      "category": "leafy",
      "months": {
        "sow": [
          1,
          2,
          3,
          4,
          5,
          6,
          7,
          8,
          9,
          10
        ],
        "plant": [
          1,
          2,
          3,
          4,
          5,
          6,
          7,
          8,
          9,
          10
        ],
        "harvest": [
          2,
          3,
          4,
          5,
          6,
          7,
          8,
          9,
          10,
          11
        ]
      },
      "details": {
        "planting": {
          "seed_depth_cm": 0.3,
          "spacing_cm": {
            "in_row": 2,
            "between_rows": 10
          }
        },
        "sunlight": "Part shade",
        "where": "Shallow trays/window boxes",
        "protection": {
          "fleece": "protect early/late season"
        },
        "tips": [
          "Harvest baby leaves repeatedly"
        ]
      },
      "containers": {
        "min_pot_diameter_cm": 18,
        "min_depth_cm": 10
      },
      "notes": ""
    },
    {
      "name": "Spinach (true)",
      "category": "leafy",
      "months": {
        "sow": [
          1,
          2,
          3,
          7,
          8,
          9
        ],
        "plant": [
          2,
          3,
          7,
          8
        ],
        "harvest": [
          2,
          3,
          4,
          7,
          8,
          9,
          10
        ]
      },
      "details": {
        "planting": {
          "seed_depth_cm": 1.5,
          "spacing_cm": {
            "in_row": 10,
            "between_rows": 25
          }
        },
        "sunlight": "Part shade/cool",
        "where": "Pots/beds",
        "protection": {
          "fleece": "protect from cold snaps; harden off before planting out"
        },
        "tips": [
          "Bolts in heat—keep cool and moist"
        ]
      },
      "containers": {
        "min_pot_diameter_cm": 22,
        "min_depth_cm": 20
      },
      "notes": ""
    },
    {
      "name": "Perpetual spinach (leaf beet)",
      "category": "leafy",
      "months": {
        "sow": [
          2,
          3,
          4,
          5,
          6
        ],
        "plant": [
          4,
          5,
          6
        ],
        "harvest": [
          5,
          6,
          7,
          8,
          9,
          10,
          11
        ]
      },
      "details": {
        "planting": {
          "seed_depth_cm": 2,
          "spacing_cm": {
            "in_row": 25,
            "between_rows": 35
          }
        },
        "sunlight": "Sun/part",
        "where": "Pots/beds",
        "protection": {
          "fleece": "protect from cold snaps; harden off before planting out"
        },
        "tips": [
          "Pick outer leaves; very hardy & long-lived"
        ]
      },
      "containers": {
        "min_pot_diameter_cm": 26,
        "min_depth_cm": 24
      },
      "notes": ""
    },
    {
      "name": "Swiss chard (rainbow)",
      "category": "leafy",
      "months": {
        "sow": [
          2,
          3,
          4,
          5,
          6
        ],
        "plant": [
          4,
          5,
          6
        ],
        "harvest": [
          5,
          6,
          7,
          8,
          9,
          10,
          11
        ]
      },
      "details": {
        "planting": {
          "seed_depth_cm": 2,
          "spacing_cm": {
            "in_row": 25,
            "between_rows": 35
          }
        },
        "sunlight": "Sun/part",
        "where": "Pots/beds",
        "protection": {
          "fleece": "protect from cold snaps; harden off before planting out"
        },
        "tips": [
          "Colourful stems; remove oldest leaves"
        ]
      },
      "containers": {
        "min_pot_diameter_cm": 26,
        "min_depth_cm": 24
      },
      "notes": ""
    },
    {
      "name": "Kale – dwarf curly",
      "category": "leafy",
      "months": {
        "sow": [
          2,
          3,
          4
        ],
        "plant": [
          4,
          5
        ],
        "harvest": [
          0,
          1,
          9,
          10,
          11
        ]
      },
      "details": {
        "planting": {
          "seed_depth_cm": 1.5,
          "spacing_cm": {
            "in_row": 45,
            "between_rows": 45
          }
        },
        "sunlight": "Sun/part",
        "where": "Large pots/beds",
        "protection": {
          "netting": "bird netting vs pigeons",
          "fleece": "protect from cold snaps; harden off before planting out",
          "mesh": "insect mesh vs cabbage pests"
        },
        "tips": [
          "Pick side leaves through winter; firm in well"
        ]
      },
      "containers": {
        "min_pot_diameter_cm": 35,
        "min_depth_cm": 30
      },
      "notes": ""
    },
    {
      "name": "Kale – cavolo nero",
      "category": "leafy",
      "months": {
        "sow": [
          2,
          3,
          4
        ],
        "plant": [
          4,
          5
        ],
        "harvest": [
          0,
          1,
          9,
          10,
          11
        ]
      },
      "details": {
        "planting": {
          "seed_depth_cm": 1.5,
          "spacing_cm": {
            "in_row": 45,
            "between_rows": 45
          }
        },
        "sunlight": "Sun",
        "where": "Large pots/beds",
        "protection": {
          "netting": "bird netting vs pigeons",
          "fleece": "protect from cold snaps; harden off before planting out",
          "mesh": "insect mesh vs cabbage pests"
        },
        "tips": [
          "Stake in wind; harvest regularly"
        ]
      },
      "containers": {
        "min_pot_diameter_cm": 35,
        "min_depth_cm": 30
      },
      "notes": ""
    },
    {
      "name": "Kale – red Russian/Siberian",
      "category": "leafy",
      "months": {
        "sow": [
          2,
          3,
          4
        ],
        "plant": [
          4,
          5
        ],
        "harvest": [
          0,
          1,
          9,
          10,
          11
        ]
      },
      "details": {
        "planting": {
          "seed_depth_cm": 1.5,
          "spacing_cm": {
            "in_row": 40,
            "between_rows": 40
          }
        },
        "sunlight": "Sun/part",
        "where": "Pots/beds",
        "protection": {
          "netting": "bird netting vs pigeons",
          "fleece": "protect from cold snaps; harden off before planting out",
          "mesh": "insect mesh vs cabbage pests"
        },
        "tips": [
          "Best flavour after frost"
        ]
      },
      "containers": {
        "min_pot_diameter_cm": 32,
        "min_depth_cm": 28
      },
      "notes": ""
    },
    {
      "name": "Cabbage – summer (Hispi/small hearts)",
      "category": "leafy",
      "months": {
        "sow": [
          2,
          3
        ],
        "plant": [
          3,
          4
        ],
        "harvest": [
          6,
          7
        ]
      },
      "details": {
        "planting": {
          "seed_depth_cm": 1,
          "spacing_cm": {
            "in_row": 40,
            "between_rows": 45
          }
        },
        "sunlight": "Sun",
        "where": "Beds/boxes (deep)",
        "protection": {
          "netting": "bird netting vs pigeons",
          "mesh": "insect mesh vs cabbage root fly & caterpillars"
        },
        "tips": [
          "Collars deter root fly; water in well"
        ]
      },
      "containers": {
        "min_pot_diameter_cm": 32,
        "min_depth_cm": 30
      },
      "notes": ""
    },
    {
      "name": "Cabbage – autumn",
      "category": "leafy",
      "months": {
        "sow": [
          3,
          4
        ],
        "plant": [
          4,
          5
        ],
        "harvest": [
          7,
          8,
          9
        ]
      },
      "details": {
        "planting": {
          "seed_depth_cm": 1,
          "spacing_cm": {
            "in_row": 45,
            "between_rows": 50
          }
        },
        "sunlight": "Sun",
        "where": "Beds/boxes",
        "protection": {
          "netting": "bird netting vs pigeons",
          "mesh": "insect mesh whole season"
        },
        "tips": [
          "Firm ground; steady water"
        ]
      },
      "containers": {
        "min_pot_diameter_cm": 34,
        "min_depth_cm": 30
      },
      "notes": ""
    },
    {
      "name": "Cabbage – winter (January King/savoy)",
      "category": "leafy",
      "months": {
        "sow": [
          2,
          3
        ],
        "plant": [
          4,
          5
        ],
        "harvest": [
          0,
          9,
          10,
          11
        ]
      },
      "details": {
        "planting": {
          "seed_depth_cm": 1,
          "spacing_cm": {
            "in_row": 50,
            "between_rows": 60
          }
        },
        "sunlight": "Sun",
        "where": "Beds/boxes",
        "protection": {
          "netting": "bird netting vs pigeons",
          "mesh": "protect from caterpillars until late season"
        },
        "tips": [
          "Very hardy"
        ]
      },
      "containers": {
        "min_pot_diameter_cm": 36,
        "min_depth_cm": 32
      },
      "notes": ""
    },
    {
      "name": "Cabbage – red",
      "category": "leafy",
      "months": {
        "sow": [
          2,
          3
        ],
        "plant": [
          4,
          5
        ],
        "harvest": [
          8,
          9
        ]
      },
      "details": {
        "planting": {
          "seed_depth_cm": 1,
          "spacing_cm": {
            "in_row": 45,
            "between_rows": 50
          }
        },
        "sunlight": "Sun",
        "where": "Beds/boxes",
        "protection": {
          "netting": "bird netting vs pigeons",
          "mesh": "caterpillars/root fly"
        },
        "tips": [
          "Net against pigeons"
        ]
      },
      "containers": {
        "min_pot_diameter_cm": 34,
        "min_depth_cm": 30
      },
      "notes": ""
    },
    {
      "name": "Chinese cabbage (napa)",
      "category": "leafy",
      "months": {
        "sow": [
          6,
          7,
          8
        ],
        "plant": [
          7,
          8
        ],
        "harvest": [
          8,
          9
        ]
      },
      "details": {
        "planting": {
          "seed_depth_cm": 1,
          "spacing_cm": {
            "in_row": 30,
            "between_rows": 35
          }
        },
        "sunlight": "Sun/part",
        "where": "Beds/boxes",
        "protection": {
          "mesh": "0.8–1.3mm insect mesh vs flea beetle (Apr–Sep)"
        },
        "tips": [
          "Autumn sowing avoids bolting"
        ]
      },
      "containers": {
        "min_pot_diameter_cm": 28,
        "min_depth_cm": 26
      },
      "notes": ""
    },
    {
      "name": "Pak choi",
      "category": "leafy",
      "months": {
        "sow": [
          3,
          4,
          5,
          6,
          7,
          8
        ],
        "plant": [
          6,
          7
        ],
        "harvest": [
          4,
          5,
          6,
          7,
          8,
          9
        ]
      },
      "details": {
        "planting": {
          "seed_depth_cm": 1,
          "spacing_cm": {
            "in_row": 20,
            "between_rows": 25
          }
        },
        "sunlight": "Part shade",
        "where": "Pots/boxes",
        "protection": {
          "mesh": "0.8–1.3mm insect mesh vs flea beetle (Apr–Sep)"
        },
        "tips": [
          "Fast; water well in dry spells"
        ]
      },
      "containers": {
        "min_pot_diameter_cm": 24,
        "min_depth_cm": 22
      },
      "notes": ""
    },
    {
      "name": "Tatsoi",
      "category": "leafy",
      "months": {
        "sow": [
          2,
          3,
          4,
          5,
          6,
          7,
          8,
          9
        ],
        "plant": [
          6,
          7
        ],
        "harvest": [
          4,
          5,
          6,
          7,
          8,
          9
        ]
      },
      "details": {
        "planting": {
          "seed_depth_cm": 1,
          "spacing_cm": {
            "in_row": 20,
            "between_rows": 25
          }
        },
        "sunlight": "Part shade",
        "where": "Pots/boxes",
        "protection": {
          "mesh": "0.8–1.3mm insect mesh vs flea beetle (Apr–Sep)"
        },
        "tips": [
          "Rosettes tolerate cold well"
        ]
      },
      "containers": {
        "min_pot_diameter_cm": 22,
        "min_depth_cm": 20
      },
      "notes": ""
    },
    {
      "name": "Mizuna",
      "category": "leafy",
      "months": {
        "sow": [
          2,
          3,
          4,
          5,
          6,
          7,
          8,
          9
        ],
        "plant": [
          6,
          7
        ],
        "harvest": [
          4,
          5,
          6,
          7,
          8,
          9
        ]
      },
      "details": {
        "planting": {
          "seed_depth_cm": 1,
          "spacing_cm": {
            "in_row": 15,
            "between_rows": 20
          }
        },
        "sunlight": "Part shade",
        "where": "Pots/boxes",
        "protection": {
          "mesh": "0.8–1.3mm insect mesh vs flea beetle (Apr–Sep)"
        },
        "tips": [
          "Cut-and-come again"
        ]
      },
      "containers": {
        "min_pot_diameter_cm": 20,
        "min_depth_cm": 18
      },
      "notes": ""
    },
    {
      "name": "Mibuna",
      "category": "leafy",
      "months": {
        "sow": [
          2,
          3,
          4,
          5,
          6,
          7,
          8,
          9
        ],
        "plant": [
          6,
          7
        ],
        "harvest": [
          4,
          5,
          6,
          7,
          8,
          9
        ]
      },
      "details": {
        "planting": {
          "seed_depth_cm": 1,
          "spacing_cm": {
            "in_row": 15,
            "between_rows": 20
          }
        },
        "sunlight": "Part shade",
        "where": "Pots/boxes",
        "protection": {
          "mesh": "0.8–1.3mm insect mesh vs flea beetle (Apr–Sep)"
        },
        "tips": [
          "Milder than mizuna"
        ]
      },
      "containers": {
        "min_pot_diameter_cm": 20,
        "min_depth_cm": 18
      },
      "notes": ""
    },
    {
      "name": "Komatsuna (mustard spinach)",
      "category": "leafy",
      "months": {
        "sow": [
          2,
          3,
          4,
          5,
          6,
          7,
          8,
          9
        ],
        "plant": [
          6,
          7
        ],
        "harvest": [
          4,
          5,
          6,
          7,
          8,
          9
        ]
      },
      "details": {
        "planting": {
          "seed_depth_cm": 1,
          "spacing_cm": {
            "in_row": 20,
            "between_rows": 25
          }
        },
        "sunlight": "Part shade",
        "where": "Pots/boxes",
        "protection": {
          "mesh": "0.8–1.3mm insect mesh vs flea beetle (Apr–Sep)"
        },
        "tips": [
          "Heat tolerant for a brassica leaf"
        ]
      },
      "containers": {
        "min_pot_diameter_cm": 22,
        "min_depth_cm": 20
      },
      "notes": ""
    },
    {
      "name": "Choi sum",
      "category": "leafy",
      "months": {
        "sow": [
          2,
          3,
          4,
          5,
          6,
          7,
          8,
          9
        ],
        "plant": [
          6,
          7
        ],
        "harvest": [
          4,
          5,
          6,
          7,
          8,
          9
        ]
      },
      "details": {
        "planting": {
          "seed_depth_cm": 1,
          "spacing_cm": {
            "in_row": 20,
            "between_rows": 25
          }
        },
        "sunlight": "Part shade",
        "where": "Pots/boxes",
        "protection": {
          "mesh": "0.8–1.3mm insect mesh vs flea beetle (Apr–Sep)"
        },
        "tips": [
          "Harvest flowering stems tender"
        ]
      },
      "containers": {
        "min_pot_diameter_cm": 22,
        "min_depth_cm": 20
      },
      "notes": ""
    },
    {
      "name": "Mustard greens (various)",
      "category": "leafy",
      "months": {
        "sow": [
          2,
          3,
          4,
          5,
          6,
          7,
          8,
          9
        ],
        "plant": [
          6,
          7
        ],
        "harvest": [
          4,
          5,
          6,
          7,
          8,
          9
        ]
      },
      "details": {
        "planting": {
          "seed_depth_cm": 1,
          "spacing_cm": {
            "in_row": 15,
            "between_rows": 20
          }
        },
        "sunlight": "Part shade",
        "where": "Pots/boxes",
        "protection": {
          "mesh": "0.8–1.3mm insect mesh vs flea beetle (Apr–Sep)"
        },
        "tips": [
          "Peppery leaves; quick"
        ]
      },
      "containers": {
        "min_pot_diameter_cm": 20,
        "min_depth_cm": 18
      },
      "notes": ""
    },
    {
      "name": "Rocket (arugula)",
      "category": "leafy",
      "months": {
        "sow": [
          1,
          2,
          3,
          4,
          5,
          6,
          7,
          8,
          9
        ],
        "plant": [
          6,
          7
        ],
        "harvest": [
          2,
          3,
          4,
          5,
          6,
          7,
          8,
          9,
          10
        ]
      },
      "details": {
        "planting": {
          "seed_depth_cm": 1,
          "spacing_cm": {
            "in_row": 15,
            "between_rows": 20
          }
        },
        "sunlight": "Part shade",
        "where": "Pots/boxes",
        "protection": {
          "mesh": "0.8–1.3mm insect mesh vs flea beetle (Apr–Sep)"
        },
        "tips": [
          "Succession sow monthly"
        ]
      },
      "containers": {
        "min_pot_diameter_cm": 20,
        "min_depth_cm": 18
      },
      "notes": ""
    },
    {
      "name": "Wild rocket (Diplotaxis)",
      "category": "leafy",
      "months": {
        "sow": [
          1,
          2,
          3,
          4,
          5,
          6,
          7,
          8,
          9
        ],
        "plant": [
          6,
          7
        ],
        "harvest": [
          2,
          3,
          4,
          5,
          6,
          7,
          8,
          9,
          10
        ]
      },
      "details": {
        "planting": {
          "seed_depth_cm": 0.5,
          "spacing_cm": {
            "in_row": 15,
            "between_rows": 20
          }
        },
        "sunlight": "Part shade",
        "where": "Pots/beds",
        "protection": {
          "mesh": "0.8–1.3mm insect mesh vs flea beetle (Apr–Sep)"
        },
        "tips": [
          "Perennial-ish; spicier"
        ]
      },
      "containers": {
        "min_pot_diameter_cm": 20,
        "min_depth_cm": 18
      },
      "notes": ""
    },
    {
      "name": "Endive (frisée)",
      "category": "leafy",
      "months": {
        "sow": [
          6,
          7,
          8
        ],
        "plant": [
          7,
          8
        ],
        "harvest": [
          9,
          10
        ]
      },
      "details": {
        "planting": {
          "seed_depth_cm": 0.8,
          "spacing_cm": {
            "in_row": 25,
            "between_rows": 30
          }
        },
        "sunlight": "Sun/part",
        "where": "Beds/boxes",
        "protection": {
          "fleece": "protect from cold snaps; harden off before planting out"
        },
        "tips": [
          "Blanch hearts if desired"
        ]
      },
      "containers": {
        "min_pot_diameter_cm": 24,
        "min_depth_cm": 22
      },
      "notes": ""
    },
    {
      "name": "Escarole",
      "category": "leafy",
      "months": {
        "sow": [
          6,
          7,
          8
        ],
        "plant": [
          7,
          8
        ],
        "harvest": [
          9,
          10
        ]
      },
      "details": {
        "planting": {
          "seed_depth_cm": 0.8,
          "spacing_cm": {
            "in_row": 25,
            "between_rows": 30
          }
        },
        "sunlight": "Sun/part",
        "where": "Beds/boxes",
        "protection": {
          "fleece": "protect from cold snaps; harden off before planting out"
        },
        "tips": [
          "Hardy autumn salad"
        ]
      },
      "containers": {
        "min_pot_diameter_cm": 24,
        "min_depth_cm": 22
      },
      "notes": ""
    },
    {
      "name": "Radicchio",
      "category": "leafy",
      "months": {
        "sow": [
          6,
          7
        ],
        "plant": [
          7,
          8
        ],
        "harvest": [
          9,
          10
        ]
      },
      "details": {
        "planting": {
          "seed_depth_cm": 1,
          "spacing_cm": {
            "in_row": 25,
            "between_rows": 30
          }
        },
        "sunlight": "Sun/part",
        "where": "Beds/boxes",
        "protection": {
          "fleece": "protect from cold snaps; harden off before planting out"
        },
        "tips": [
          "Colour improves with cold"
        ]
      },
      "containers": {
        "min_pot_diameter_cm": 24,
        "min_depth_cm": 22
      },
      "notes": ""
    },
    {
      "name": "Corn salad (lamb’s lettuce/mâche)",
      "category": "leafy",
      "months": {
        "sow": [
          7,
          8,
          9
        ],
        "plant": [
          9,
          10
        ],
        "harvest": [
          9,
          10,
          11
        ]
      },
      "details": {
        "planting": {
          "seed_depth_cm": 1,
          "spacing_cm": {
            "in_row": 10,
            "between_rows": 20
          }
        },
        "sunlight": "Part shade/cool",
        "where": "Pots/boxes",
        "protection": {
          "fleece": "protect from cold snaps; harden off before planting out"
        },
        "tips": [
          "Great winter salad"
        ]
      },
      "containers": {
        "min_pot_diameter_cm": 20,
        "min_depth_cm": 18
      },
      "notes": ""
    },
    {
      "name": "Claytonia (winter purslane/miner’s lettuce)",
      "category": "leafy",
      "months": {
        "sow": [
          7,
          8,
          9
        ],
        "plant": [
          9,
          10
        ],
        "harvest": [
          9,
          10,
          11
        ]
      },
      "details": {
        "planting": {
          "seed_depth_cm": 0.5,
          "spacing_cm": {
            "in_row": 8,
            "between_rows": 15
          }
        },
        "sunlight": "Shade/part",
        "where": "Pots/shady spots",
        "protection": {
          "fleece": "protect from cold snaps; harden off before planting out"
        },
        "tips": [
          "Very shade-tolerant winter salad"
        ]
      },
      "containers": {
        "min_pot_diameter_cm": 18,
        "min_depth_cm": 12
      },
      "notes": ""
    },
    {
      "name": "Watercress (pot-grown)",
      "category": "leafy",
      "months": {
        "sow": [
          2,
          3,
          4,
          5,
          6,
          7,
          8
        ],
        "plant": [
          4,
          5,
          6,
          7,
          8
        ],
        "harvest": [
          4,
          5,
          6,
          7,
          8
        ]
      },
      "details": {
        "planting": {
          "seed_depth_cm": 0.5,
          "spacing_cm": {
            "in_row": 10,
            "between_rows": 15
          }
        },
        "sunlight": "Part shade",
        "where": "Self-watering pots/trays kept moist",
        "protection": {},
        "tips": [
          "Use clean water; do not collect wild"
        ]
      },
      "containers": {
        "min_pot_diameter_cm": 22,
        "min_depth_cm": 18
      },
      "notes": ""
    },
    {
      "name": "Land cress (American cress)",
      "category": "leafy",
      "months": {
        "sow": [
          7,
          8,
          9
        ],
        "plant": [
          9,
          10
        ],
        "harvest": [
          9,
          10,
          11
        ]
      },
      "details": {
        "planting": {
          "seed_depth_cm": 0.5,
          "spacing_cm": {
            "in_row": 8,
            "between_rows": 15
          }
        },
        "sunlight": "Part shade/cool",
        "where": "Pots/beds",
        "protection": {
          "fleece": "protect from cold snaps; harden off before planting out"
        },
        "tips": [
          "Peppery leaves; great winter stand-in for watercress"
        ]
      },
      "containers": {
        "min_pot_diameter_cm": 18,
        "min_depth_cm": 14
      },
      "notes": ""
    },
    {
      "name": "Sorrel – garden",
      "category": "leafy",
      "months": {
        "sow": [
          2,
          3,
          4,
          5,
          6,
          7,
          8,
          9
        ],
        "plant": [
          2,
          3,
          4,
          5,
          6,
          7,
          8,
          9
        ],
        "harvest": [
          2,
          3,
          4,
          5,
          6,
          7,
          8,
          9
        ]
      },
      "details": {
        "planting": {
          "seed_depth_cm": 0.5,
          "spacing_cm": {
            "in_row": 30,
            "between_rows": 40
          }
        },
        "sunlight": "Sun/part",
        "where": "Pots/beds",
        "protection": {},
        "tips": [
          "Perennial; tangy leaves"
        ]
      },
      "containers": {
        "min_pot_diameter_cm": 24,
        "min_depth_cm": 22
      },
      "notes": ""
    },
    {
      "name": "Sorrel – red veined",
      "category": "leafy",
      "months": {
        "sow": [
          2,
          3,
          4,
          5,
          6,
          7,
          8,
          9
        ],
        "plant": [
          2,
          3,
          4,
          5,
          6,
          7,
          8,
          9
        ],
        "harvest": [
          2,
          3,
          4,
          5,
          6,
          7,
          8,
          9
        ]
      },
      "details": {
        "planting": {
          "seed_depth_cm": 0.5,
          "spacing_cm": {
            "in_row": 25,
            "between_rows": 35
          }
        },
        "sunlight": "Sun/part",
        "where": "Pots/beds",
        "protection": {},
        "tips": [
          "Great for salads; ornamental"
        ]
      },
      "containers": {
        "min_pot_diameter_cm": 22,
        "min_depth_cm": 20
      },
      "notes": ""
    },
    {
      "name": "Nasturtium (edible leaves/flowers)",
      "category": "leafy",
      "months": {
        "sow": [
          2,
          3,
          4
        ],
        "plant": [
          4,
          5
        ],
        "harvest": [
          4,
          5,
          6,
          7,
          8,
          9
        ]
      },
      "details": {
        "planting": {
          "seed_depth_cm": 1.5,
          "spacing_cm": {
            "in_row": 30,
            "between_rows": 40
          }
        },
        "sunlight": "Sun/part",
        "where": "Pots/hanging/ground cover",
        "protection": {},
        "tips": [
          "Also acts as aphid trap crop"
        ]
      },
      "containers": {
        "min_pot_diameter_cm": 26,
        "min_depth_cm": 24
      },
      "notes": ""
    },
    {
      "name": "Calendula (pot marigold, edible)",
      "category": "leafy",
      "months": {
        "sow": [
          2,
          3,
          4,
          5
        ],
        "plant": [
          4,
          5
        ],
        "harvest": [
          4,
          5,
          6,
          7,
          8,
          9
        ]
      },
      "details": {
        "planting": {
          "seed_depth_cm": 1,
          "spacing_cm": {
            "in_row": 25,
            "between_rows": 30
          }
        },
        "sunlight": "Sun",
        "where": "Pots/beds",
        "protection": {},
        "tips": [
          "Deadhead to prolong flowering"
        ]
      },
      "containers": {
        "min_pot_diameter_cm": 22,
        "min_depth_cm": 20
      },
      "notes": ""
    },
    {
      "name": "Sea kale (blanched shoots/leaves)",
      "category": "leafy",
      "months": {
        "sow": [
          2,
          3
        ],
        "plant": [
          9,
          10
        ],
        "harvest": [
          2,
          3,
          4,
          5
        ]
      },
      "details": {
        "planting": {
          "seed_depth_cm": 1.5,
          "spacing_cm": {
            "in_row": 60,
            "between_rows": 75
          }
        },
        "sunlight": "Sun",
        "where": "Large pots/ground",
        "protection": {},
        "tips": [
          "Perennial; can force/blanch in spring"
        ]
      },
      "containers": {
        "min_pot_diameter_cm": 40,
        "min_depth_cm": 40
      },
      "notes": ""
    },
    {
      "name": "Cardoon (leaf stalks blanched)",
      "category": "leafy",
      "months": {
        "sow": [
          2,
          3
        ],
        "plant": [
          4,
          5
        ],
        "harvest": [
          8,
          9
        ]
      },
      "details": {
        "planting": {
          "seed_depth_cm": 1.5,
          "spacing_cm": {
            "in_row": 90,
            "between_rows": 120
          }
        },
        "sunlight": "Sun",
        "where": "Very large pots/ground",
        "protection": {},
        "tips": [
          "Tie/blanch stalks before harvest"
        ]
      },
      "containers": {
        "min_pot_diameter_cm": 50,
        "min_depth_cm": 45
      },
      "notes": ""
    }
  ]
}